nonebot_plugin_guild_patch/__init__.py
nonebot_plugin_guild_patch/models.py
nonebot_plugin_guild_patch/permission.py
nonebot_plugin_guild_patch/py.typed
nonebot_plugin_guild_patch_remix-0.2.4.dist-info/LICENSE
nonebot_plugin_guild_patch_remix-0.2.4.dist-info/METADATA
nonebot_plugin_guild_patch_remix-0.2.4.dist-info/WHEEL
nonebot_plugin_guild_patch_remix-0.2.4.dist-info/RECORD
