Metadata-Version: 2.1
Name: nonebot-plugin-guild-patch-remix
Version: 0.2.4
Summary: Patch plugin(remix) for NoneBot2 QQ guild (go-cqhttp) support.
Home-page: https://github.com/zhzhongshi/nonebot-plugin-guild-patch-remix
License: MIT
Author: 17TheWord
Author-email: 17TheWord@gmail.com
Requires-Python: >=3.9,<4.0
Classifier: License :: OSI Approved :: MIT License
Classifier: Programming Language :: Python :: 3
Classifier: Programming Language :: Python :: 3.9
Classifier: Programming Language :: Python :: 3.10
Classifier: Programming Language :: Python :: 3.11
Classifier: Programming Language :: Python :: 3.12
Requires-Dist: nonebot-adapter-onebot (>=2.4.3,<3.0.0)
Requires-Dist: nonebot2 (>=2.2.1,<3.0.0)
Project-URL: Repository, https://github.com/zhzhongshi/nonebot-plugin-guild-patch-remix
